flask_wxpay
