Metadata-Version: 1.0
Name: Flask-WXPay
Version: 0.1.15
Summary: Flask Extension for WeChat Pay.
Home-page: https://github.com/codeif/Flask-WXPay
Author: codeif
Author-email: me@codeif.com
License: MIT
Platform: UNKNOWN
